MANIFEST.in
README
__init__.py
__pkginfo__.py
setup.py
views.py
xhtml2fo.py
./__init__.py
./__pkginfo__.py
./views.py
./xhtml2fo.py
./test/pytestconf.py
./test/test_pdfexport.py
./test/unittest_pdf.py
cubicweb_pdfexport.egg-info/PKG-INFO
cubicweb_pdfexport.egg-info/SOURCES.txt
cubicweb_pdfexport.egg-info/dependency_links.txt
cubicweb_pdfexport.egg-info/requires.txt
cubicweb_pdfexport.egg-info/top_level.txt
data/pdf_icon.gif
i18n/en.po
i18n/es.po
i18n/fr.po
test/pytestconf.py
test/test_pdfexport.py
test/unittest_pdf.py