Metadata-Version: 1.0
Name: cubicweb-pdfexport
Version: 0.1.0
Summary: export any page as a pdf document
Home-page: http://www.cubicweb.org/project/cubicweb-pdfexport
Author: LOGILAB S.A. (Paris, FRANCE)
Author-email: contact@logilab.fr
License: LGPL
Platform: UNKNOWN
